LICENSE
MANIFEST.in
README.rst
requirements.txt
setup.py
Flask_Boost.egg-info/PKG-INFO
Flask_Boost.egg-info/SOURCES.txt
Flask_Boost.egg-info/dependency_links.txt
Flask_Boost.egg-info/entry_points.txt
Flask_Boost.egg-info/requires.txt
Flask_Boost.egg-info/top_level.txt
flask_boost/__init__.py
flask_boost/cli.py
flask_boost/project/.gitignore
flask_boost/project/README.md
flask_boost/project/bower.json
flask_boost/project/fabfile.py
flask_boost/project/gulpfile.js
flask_boost/project/manage.py
flask_boost/project/package.json
flask_boost/project/pylintrc
flask_boost/project/requirements.txt
flask_boost/project/wsgi.py
flask_boost/project/application/__init__.py
flask_boost/project/application/fis-conf.js
flask_boost/project/application/controllers/__init__.py
flask_boost/project/application/controllers/account.py
flask_boost/project/application/controllers/site.py
flask_boost/project/application/forms/__init__.py
flask_boost/project/application/forms/_helper.py
flask_boost/project/application/forms/account.py
flask_boost/project/application/macros/_form.html
flask_boost/project/application/macros/_utils.html
flask_boost/project/application/macros/user/users/_users.html
flask_boost/project/application/macros/user/users/_users.js
flask_boost/project/application/macros/user/users/_users.less
flask_boost/project/application/models/__init__.py
flask_boost/project/application/models/_base.py
flask_boost/project/application/models/user.py
flask_boost/project/application/pages/layout.html
flask_boost/project/application/pages/account/signin/signin.css
flask_boost/project/application/pages/account/signin/signin.html
flask_boost/project/application/pages/account/signin/signin.js
flask_boost/project/application/pages/account/signin/signin.less
flask_boost/project/application/pages/account/signup/signup.css
flask_boost/project/application/pages/account/signup/signup.html
flask_boost/project/application/pages/account/signup/signup.js
flask_boost/project/application/pages/account/signup/signup.less
flask_boost/project/application/pages/site/403/403.html
flask_boost/project/application/pages/site/404/404.html
flask_boost/project/application/pages/site/500/500.html
